hiveql/__init__.py
hiveql/__main__.py
hiveql/constants.py
hiveql/install.py
hiveql/kernel.py
hiveql/main.py
hiveql/tool_sql.py
hiveql/resources/custom.css
hiveql/resources/logo-32x32.png
hiveql/resources/logo-64x64.png
hiveqlKernel-1.0.20.dist-info/LICENSE
hiveqlKernel-1.0.20.dist-info/METADATA
hiveqlKernel-1.0.20.dist-info/WHEEL
hiveqlKernel-1.0.20.dist-info/entry_points.txt
hiveqlKernel-1.0.20.dist-info/top_level.txt
hiveqlKernel-1.0.20.dist-info/RECORD
