Metadata-Version: 2.1
Name: hiveqlKernel
Version: 1.0.20
Summary: HiveQL Kernel
Home-page: https://github.com/EDS-APHP/HiveQLKernel
Author: APHP - EDS
Author-email: UNKNOWN
License: MIT
Keywords: Hive HiveQL PyHive Kernel Ipykernel
Platform: UNKNOWN
Requires-Dist: ipykernel (==4.*)
Requires-Dist: jupyter-client (==5.*)
Requires-Dist: jupyter-core (==4.*)
Requires-Dist: pandas (==0.23.*)
Requires-Dist: pyhive (==0.6.*)
Requires-Dist: sasl (==0.2.*)
Requires-Dist: thrift-sasl (==0.3.*)
Requires-Dist: pytest (==4.2.*)
